pybitblock/PyBlock.py
pybitblock/SPV/__init__.py
pybitblock/SPV/apisnd.py
pybitblock/SPV/clone.py
pybitblock/SPV/config/bclock.conf
pybitblock/SPV/config/init.conf
pybitblock/SPV/config/pyblocksettings.conf
pybitblock/SPV/config/pyblocksettingsClock.conf
pybitblock/SPV/config/selection.conf
pybitblock/SPV/console.py
pybitblock/SPV/donation.py
pybitblock/SPV/feed.py
pybitblock/SPV/grpc_generated/router_pb2.py
pybitblock/SPV/grpc_generated/router_pb2_grpc.py
pybitblock/SPV/grpc_generated/rpc_pb2.py
pybitblock/SPV/grpc_generated/rpc_pb2_grpc.py
pybitblock/SPV/lnd.py
pybitblock/SPV/logic.py
pybitblock/SPV/logos.py
pybitblock/SPV/mempool-cli
pybitblock/SPV/nodeconnection.py
pybitblock/SPV/pblogo.py
pybitblock/SPV/ppi.py
pybitblock/SPV/sha256.py
pybitblock/SPV/spvblock.py
pybitblock/SPV/sysinf.py
pybitblock/SPV/terminal_matrix/LICENSE.GPL
pybitblock/SPV/terminal_matrix/README.md
pybitblock/SPV/terminal_matrix/matrix.py
pybitblock/__init__.py
pybitblock/apisnd.py
pybitblock/bitcoin.pdf
pybitblock/clockscript.py
pybitblock/clockscriptREMOTE.py
pybitblock/clone.py
pybitblock/console.py
pybitblock/donation.py
pybitblock/feed.py
pybitblock/grpc_generated/router_pb2.py
pybitblock/grpc_generated/router_pb2_grpc.py
pybitblock/grpc_generated/rpc_pb2.py
pybitblock/grpc_generated/rpc_pb2_grpc.py
pybitblock/images/bitcoin-donation.png
pybitblock/images/codeimage.png
pybitblock/images/keysend.png
pybitblock/images/qrcode.png
pybitblock/lnd.py
pybitblock/logic.py
pybitblock/logos.py
pybitblock/mempool-cli
pybitblock/mempoolclock.py
pybitblock/nodeconnection.py
pybitblock/pblogo.py
pybitblock/ppi.py
pybitblock/rebalance.py
pybitblock/resources/images/EYDhHM1X0AAd8UP.PNG
pybitblock/resources/images/Logo.PNG
pybitblock/resources/images/REST1.PNG
pybitblock/resources/images/REST1REMOTE.PNG
pybitblock/resources/images/REST2.PNG
pybitblock/resources/images/REST2REMOTE.PNG
pybitblock/resources/images/REST3.PNG
pybitblock/resources/images/REST3REMOTE.PNG
pybitblock/resources/images/REST4.PNG
pybitblock-2.7.1.dist-info/LICENSE
pybitblock-2.7.1.dist-info/METADATA
pybitblock-2.7.1.dist-info/WHEEL
pybitblock-2.7.1.dist-info/entry_points.txt
pybitblock-2.7.1.dist-info/RECORD
