Metadata-Version: 2.1
Name: pybitblock
Version: 2.7.1
Summary: ℙ𝕪𝔹𝕃𝕆ℂ𝕂 𝕚𝕥𝕤 𝕒 𝔹𝕚𝕥𝕔𝕠𝕚𝕟 𝔻𝕒𝕤𝕙𝕓𝕠𝕒𝕣𝕕 𝕨𝕚𝕥𝕙 ℂ𝕪𝕡𝕙𝕖𝕣𝕡𝕦𝕟𝕜 𝕒𝕖𝕤𝕥𝕙𝕖𝕥𝕚𝕔.
Home-page: https://github.com/curly60e/pyblock
License: MIT
Author: curly60e
Author-email: curly60e@piserver.xyz
Requires-Python: >=3.12,<4.0
Classifier: License :: OSI Approved :: MIT License
Classifier: Programming Language :: Python :: 3
Classifier: Programming Language :: Python :: 3.12
Requires-Dist: Pillow
Requires-Dist: art
Requires-Dist: certifi
Requires-Dist: chardet
Requires-Dist: embit
Requires-Dist: googleapis-common-protos
Requires-Dist: html2text
Requires-Dist: idna
Requires-Dist: jq
Requires-Dist: numpy
Requires-Dist: pdf2text
Requires-Dist: pdf2txt
Requires-Dist: pdfminer
Requires-Dist: protobuf
Requires-Dist: psutil
Requires-Dist: pycoingecko
Requires-Dist: python-cfonts
Requires-Dist: python-gnupg
Requires-Dist: qrcode
Requires-Dist: requests
Requires-Dist: robohash
Requires-Dist: simplejson
Requires-Dist: six
Requires-Dist: sseclient-py
Requires-Dist: termcolor
Requires-Dist: typer
Requires-Dist: urllib3
Requires-Dist: xmltodict
Project-URL: Repository, https://github.com/curly60e/pyblock
